odoo10_addon_sale_procurement_group_by_requested_date-10.0.1.0.0.99.dev6-py3.8-nspkg.pth
odoo/addons/sale_procurement_group_by_requested_date/README.rst
odoo/addons/sale_procurement_group_by_requested_date/__init__.py
odoo/addons/sale_procurement_group_by_requested_date/__manifest__.py
odoo/addons/sale_procurement_group_by_requested_date/i18n/ca.po
odoo/addons/sale_procurement_group_by_requested_date/i18n/de.po
odoo/addons/sale_procurement_group_by_requested_date/i18n/el_GR.po
odoo/addons/sale_procurement_group_by_requested_date/i18n/es.po
odoo/addons/sale_procurement_group_by_requested_date/i18n/es_ES.po
odoo/addons/sale_procurement_group_by_requested_date/i18n/es_VE.po
odoo/addons/sale_procurement_group_by_requested_date/i18n/fi.po
odoo/addons/sale_procurement_group_by_requested_date/i18n/fr.po
odoo/addons/sale_procurement_group_by_requested_date/i18n/hr.po
odoo/addons/sale_procurement_group_by_requested_date/i18n/hr_HR.po
odoo/addons/sale_procurement_group_by_requested_date/i18n/hu.po
odoo/addons/sale_procurement_group_by_requested_date/i18n/it.po
odoo/addons/sale_procurement_group_by_requested_date/i18n/nl.po
odoo/addons/sale_procurement_group_by_requested_date/i18n/nl_NL.po
odoo/addons/sale_procurement_group_by_requested_date/i18n/pt.po
odoo/addons/sale_procurement_group_by_requested_date/i18n/pt_BR.po
odoo/addons/sale_procurement_group_by_requested_date/i18n/ro.po
odoo/addons/sale_procurement_group_by_requested_date/i18n/sale_procurement_group_by_requested_date.pot
odoo/addons/sale_procurement_group_by_requested_date/i18n/sl.po
odoo/addons/sale_procurement_group_by_requested_date/i18n/tr.po
odoo/addons/sale_procurement_group_by_requested_date/i18n/tr_TR.po
odoo/addons/sale_procurement_group_by_requested_date/i18n/vi_VN.po
odoo/addons/sale_procurement_group_by_requested_date/i18n/zh_CN.po
odoo/addons/sale_procurement_group_by_requested_date/models/__init__.py
odoo/addons/sale_procurement_group_by_requested_date/models/sale_order.py
odoo10_addon_sale_procurement_group_by_requested_date-10.0.1.0.0.99.dev6.dist-info/METADATA
odoo10_addon_sale_procurement_group_by_requested_date-10.0.1.0.0.99.dev6.dist-info/WHEEL
odoo10_addon_sale_procurement_group_by_requested_date-10.0.1.0.0.99.dev6.dist-info/namespace_packages.txt
odoo10_addon_sale_procurement_group_by_requested_date-10.0.1.0.0.99.dev6.dist-info/top_level.txt
odoo10_addon_sale_procurement_group_by_requested_date-10.0.1.0.0.99.dev6.dist-info/RECORD
